forensicstore/__init__.py
forensicstore/forensicstore.py
forensicstore/hashed_file.py
forensicstore/resolver.py
forensicstore/cmd/__init__.py
forensicstore/cmd/__main__.py
forensicstore/sqlitefs/__init__.py
forensicstore-0.18.0.dist-info/LICENSE
forensicstore-0.18.0.dist-info/METADATA
forensicstore-0.18.0.dist-info/WHEEL
forensicstore-0.18.0.dist-info/entry_points.txt
forensicstore-0.18.0.dist-info/top_level.txt
forensicstore-0.18.0.dist-info/RECORD
